<odoo>
<data noupdate="1">
<record model = 'res.partner' id = "itk_initial_data_import.gemeinde10701"><field name = 'street'>Hauptgasse 8</field><field name = 'website'>http://www.andau-gemeinde.at/</field><field name = 'austria_wiki_url'>https://austria-forum.org/af/AustriaWiki/Andau</field><field name = 'latitude'>47°47′N</field><field name = 'longitude'> 17°2′O</field></record>
<record model = 'res.partner' id = "itk_initial_data_import.gemeinde10616"><field name = 'street'>Hauptplatz 3</field><field name = 'website'>www.antau.gv.at</field><field name = 'austria_wiki_url'>https://austria-forum.org/af/AustriaWiki/Antau</field><field name = 'latitude'>47°46′N</field><field name = 'longitude'> 16°29′O</field></record>
<record model = 'res.partner' id = "itk_initial_data_import.gemeinde10611"><field name = 'street'>Wiener Neustädter Straße 2</field><field name = 'website'>www.bad-sauerbrunn.at</field><field name = 'austria_wiki_url'>https://austria-forum.org/af/AustriaWiki/Bad_Sauerbrunn</field><field name = 'latitude'>47°46′N</field><field name = 'longitude'> 16°19′O</field></record>
<record model = 'res.partner' id = "itk_initial_data_import.gemeinde10901"><field name = 'street'>Joseph-Haydn-Platz 1</field><field name = 'website'>www.bad-tatzmannsdorf.at</field><field name = 'austria_wiki_url'>https://austria-forum.org/af/AustriaWiki/Bad_Tatzmannsdorf</field><field name = 'latitude'>47°20′N</field><field name = 'longitude'> 16°14′O</field></record>
<record model = 'res.partner' id = "itk_initial_data_import.gemeinde10931"><field name = 'street'>Obere Dorfstraße 5</field><field name = 'website'>www.badersdorf.at</field><field name = 'austria_wiki_url'>https://austria-forum.org/af/AustriaWiki/Badersdorf</field><field name = 'latitude'>47°12′N</field><field name = 'longitude'> 16°22′O</field></record>
<record model = 'res.partner' id = "itk_initial_data_import.gemeinde10702"><field name = 'street'>Kirchengasse 68</field><field name = 'website'>www.gemeinde-apetlon.at</field><field name = 'austria_wiki_url'>https://austria-forum.org/af/AustriaWiki/Apetlon</field><field name = 'latitude'>47°45′N</field><field name = 'longitude'> 16°50′O</field></record>
<record model = 'res.partner' id = "itk_initial_data_import.gemeinde10703"><field name = 'street'>Bahnhofplatz 5</field><field name = 'website'>www.bruckneudorf.eu</field><field name = 'austria_wiki_url'>https://austria-forum.org/af/AustriaWiki/Bruckneudorf</field><field name = 'latitude'>48°1′N</field><field name = 'longitude'> 16°46′O</field></record>
<record model = 'res.partner' id = "itk_initial_data_import.gemeinde10401"><field name = 'street'>Herrengasse 11</field><field name = 'website'>www.bocksdorf.at</field><field name = 'austria_wiki_url'>https://austria-forum.org/af/AustriaWiki/Bocksdorf</field><field name = 'latitude'>47°9′N</field><field name = 'longitude'> 16°11′O</field></record>
<record model = 'res.partner' id = "itk_initial_data_import.gemeinde10301"><field name = 'street'>Eisenstädter Straße 18</field><field name = 'website'>www.breitenbrunn.at</field><field name = 'austria_wiki_url'>https://austria-forum.org/af/AustriaWiki/Breitenbrunn_am_Neusiedler_See</field><field name = 'latitude'>47°57′N</field><field name = 'longitude'> 16°44′O</field></record>
<record model = 'res.partner' id = "itk_initial_data_import.gemeinde10402"><field name = 'street'>Höhenstraße 4</field><field name = 'website'>www.burgauberg-neudauberg.at</field><field name = 'austria_wiki_url'>https://austria-forum.org/af/AustriaWiki/Burgauberg-Neudauberg</field><field name = 'latitude'>47°9′N</field><field name = 'longitude'> 16°8′O</field></record>
<record model = 'res.partner' id = "itk_initial_data_import.gemeinde10704"><field name = 'street'>Obere Hauptstraße 12</field><field name = 'website'>www.deutsch-jahrndorf.at</field><field name = 'austria_wiki_url'>https://austria-forum.org/af/AustriaWiki/Deutsch_Jahrndorf</field><field name = 'latitude'>48°1′N</field><field name = 'longitude'> 17°6′O</field></record>
<record model = 'res.partner' id = "itk_initial_data_import.gemeinde10501"><field name = 'street'>Marktplatz 1</field><field name = 'website'>www.deutschkaltenbrunn.eu</field><field name = 'austria_wiki_url'>https://austria-forum.org/af/AustriaWiki/Deutsch_Kaltenbrunn</field><field name = 'latitude'>47°5′N</field><field name = 'longitude'> 16°6′O</field></record>
<record model = 'res.partner' id = "itk_initial_data_import.gemeinde10302"><field name = 'street'>Hauptstraße 29</field><field name = 'website'>www.donnerskirchen.at</field><field name = 'austria_wiki_url'>https://austria-forum.org/af/AustriaWiki/Donnerskirchen</field><field name = 'latitude'>47°54′N</field><field name = 'longitude'> 16°39′O</field></record>
<record model = 'res.partner' id = "itk_initial_data_import.gemeinde10802"><field name = 'street'>Marktgemeinde DraßmarktHauptstraße </field><field name = 'website'>www.drassmarkt.at</field><field name = 'austria_wiki_url'>https://austria-forum.org/af/AustriaWiki/Dra%C3%9Fmarkt</field><field name = 'latitude'>47°31′N</field><field name = 'longitude'> 16°24′O</field></record>
<record model = 'res.partner' id = "itk_initial_data_import.gemeinde10403"><field name = 'street'>Hauptplatz 1</field><field name = 'website'>www.eberau.at</field><field name = 'austria_wiki_url'>https://austria-forum.org/af/AustriaWiki/Eberau</field><field name = 'latitude'>47°6′N</field><field name = 'longitude'> 16°28′O</field></record>
<record model = 'res.partner' id = "itk_initial_data_import.gemeinde10101"><field name = 'street'>Hauptstraße 35</field><field name = 'website'>www.eisenstadt.gv.at</field><field name = 'austria_wiki_url'>https://austria-forum.org/af/AustriaWiki/Eisenstadt</field><field name = 'latitude'>47°51′N</field><field name = 'longitude'> 16°31′O</field></record>
<record model = 'res.partner' id = "itk_initial_data_import.gemeinde10502"><field name = 'street'>Kirchenstraße 2</field><field name = 'website'>www.eltendorf.at</field><field name = 'austria_wiki_url'>https://austria-forum.org/af/AustriaWiki/Eltendorf</field><field name = 'latitude'>47°1′N</field><field name = 'longitude'> 16°12′O</field></record>
<record model = 'res.partner' id = "itk_initial_data_import.gemeinde10705"><field name = 'street'>Amtshausgasse 5</field><field name = 'website'>www.frauenkirchen.info</field><field name = 'austria_wiki_url'>https://austria-forum.org/af/AustriaWiki/Frauenkirchen</field><field name = 'latitude'>47°50′N</field><field name = 'longitude'> 16°55′O</field></record>
<record model = 'res.partner' id = "itk_initial_data_import.gemeinde10706"><field name = 'street'>Hauptplatz 4</field><field name = 'website'>www.gattendorf.at</field><field name = 'austria_wiki_url'>https://austria-forum.org/af/AustriaWiki/Gattendorf_%28Burgenland%29</field><field name = 'latitude'>48°1′N</field><field name = 'longitude'> 16°59′O</field></record>
<record model = 'res.partner' id = "itk_initial_data_import.gemeinde10707"><field name = 'street'>Untere Hauptstraße 10</field><field name = 'website'>www.gols.at</field><field name = 'austria_wiki_url'>https://austria-forum.org/af/AustriaWiki/Gols</field><field name = 'latitude'>47°54′N</field><field name = 'longitude'> 16°55′O</field></record>
<record model = 'res.partner' id = "itk_initial_data_import.gemeinde10303"><field name = 'street'>Hauptstraße 37</field><field name = 'website'>www.grosshoeflein.at</field><field name = 'austria_wiki_url'>https://austria-forum.org/af/AustriaWiki/Gro%C3%9Fh%C3%B6flein</field><field name = 'latitude'>47°50′N</field><field name = 'longitude'> 16°29′O</field></record>
<record model = 'res.partner' id = "itk_initial_data_import.gemeinde10420"><field name = 'street'>Großmürbisch 120</field><field name = 'website'>www.grossmuerbisch.at</field><field name = 'austria_wiki_url'>https://austria-forum.org/af/AustriaWiki/Gro%C3%9Fm%C3%BCrbisch</field><field name = 'latitude'>47°1′N</field><field name = 'longitude'> 16°22′O</field></record>
<record model = 'res.partner' id = "itk_initial_data_import.gemeinde10804"><field name = 'street'>Obere Hauptstraße 18</field><field name = 'website'>www.grosswarasdorf.at (kroatisch)</field><field name = 'austria_wiki_url'>https://austria-forum.org/af/AustriaWiki/Gro%C3%9Fwarasdorf</field><field name = 'latitude'>47°32′N</field><field name = 'longitude'> 16°33′O</field></record>
<record model = 'res.partner' id = "itk_initial_data_import.gemeinde10405"><field name = 'street'>Hauptplatz 7</field><field name = 'website'>www.gussing.at</field><field name = 'austria_wiki_url'>https://austria-forum.org/af/AustriaWiki/G%C3%BCssing</field><field name = 'latitude'>47°4′N</field><field name = 'longitude'> 16°19′O</field></record>
<record model = 'res.partner' id = "itk_initial_data_import.gemeinde10406"><field name = 'street'>Marktplatz 1</field><field name = 'website'>www.guettenbach.at</field><field name = 'austria_wiki_url'>https://austria-forum.org/af/AustriaWiki/G%C3%BCttenbach</field><field name = 'latitude'>47°10′N</field><field name = 'longitude'> 16°17′O</field></record>
<record model = 'res.partner' id = "itk_initial_data_import.gemeinde10418"><field name = 'street'>Hackerberg 77</field><field name = 'website'>www.hackerberg.at</field><field name = 'austria_wiki_url'>https://austria-forum.org/af/AustriaWiki/Hackerberg</field><field name = 'latitude'>47°12′N</field><field name = 'longitude'> 16°6′O</field></record>
<record model = 'res.partner' id = "itk_initial_data_import.gemeinde10708"><field name = 'street'>Wiener Straße 3</field><field name = 'website'>www.halbturn.at</field><field name = 'austria_wiki_url'>https://austria-forum.org/af/AustriaWiki/Halbturn</field><field name = 'latitude'>47°52′N</field><field name = 'longitude'> 16°58′O</field></record>
<record model = 'res.partner' id = "itk_initial_data_import.gemeinde10407"><field name = 'street'>Heiligenbrunn 33</field><field name = 'website'>www.heiligenbrunn.at</field><field name = 'austria_wiki_url'>https://austria-forum.org/af/AustriaWiki/Heiligenbrunn</field><field name = 'latitude'>47°2′N</field><field name = 'longitude'> 16°25′O</field></record>
<record model = 'res.partner' id = "itk_initial_data_import.gemeinde10424"><field name = 'street'>Heugraben 120</field><field name = 'website'>www.heugraben.at</field><field name = 'austria_wiki_url'>https://austria-forum.org/af/AustriaWiki/Heugraben</field><field name = 'latitude'>47°7′N</field><field name = 'longitude'> 16°11′O</field></record>
<record model = 'res.partner' id = "itk_initial_data_import.gemeinde10503"><field name = 'street'>Untere Hauptstraße 1</field><field name = 'website'>www.heiligenkreuz-lafnitztal.at</field><field name = 'austria_wiki_url'>https://austria-forum.org/af/AustriaWiki/Heiligenkreuz_im_Lafnitztal</field><field name = 'latitude'>46°59′N</field><field name = 'longitude'> 16°16′O</field></record>
<record model = 'res.partner' id = "itk_initial_data_import.gemeinde10805"><field name = 'street'>Hauptstraße 43</field><field name = 'website'>www.horitschon.at</field><field name = 'austria_wiki_url'>https://austria-forum.org/af/AustriaWiki/Horitschon</field><field name = 'latitude'>47°35′N</field><field name = 'longitude'> 16°33′O</field></record>
<record model = 'res.partner' id = "itk_initial_data_import.gemeinde10709"><field name = 'street'>Obere Hauptstraße 2-4</field><field name = 'website'>gemeinde-illmitz.at/</field><field name = 'austria_wiki_url'>https://austria-forum.org/af/AustriaWiki/Illmitz</field><field name = 'latitude'>47°46′N</field><field name = 'longitude'> 16°48′O</field></record>
<record model = 'res.partner' id = "itk_initial_data_import.gemeinde10421"><field name = 'street'>Inzenhof 42</field><field name = 'website'>www.inzenhof.at</field><field name = 'austria_wiki_url'>https://austria-forum.org/af/AustriaWiki/Inzenhof_%28Burgenland%29</field><field name = 'latitude'>47°1′N</field><field name = 'longitude'> 16°19′O</field></record>
<record model = 'res.partner' id = "itk_initial_data_import.gemeinde10504"><field name = 'street'>Hauptplatz 5a</field><field name = 'website'>www.jennersdorf.eu</field><field name = 'austria_wiki_url'>https://austria-forum.org/af/AustriaWiki/Jennersdorf</field><field name = 'latitude'>46°56′N</field><field name = 'longitude'> 16°8′O</field></record>
<record model = 'res.partner' id = "itk_initial_data_import.gemeinde10710"><field name = 'street'>Untere Hauptstraße 23</field><field name = 'website'>www.jois.at</field><field name = 'austria_wiki_url'>https://austria-forum.org/af/AustriaWiki/Jois</field><field name = 'latitude'>47°58′N</field><field name = 'longitude'> 16°48′O</field></record>
<record model = 'res.partner' id = "itk_initial_data_import.gemeinde10806"><field name = 'street'>Hauptstraße 57</field><field name = 'website'>www.kaisersdorf.com</field><field name = 'austria_wiki_url'>https://austria-forum.org/af/AustriaWiki/Kaisersdorf</field><field name = 'latitude'>47°32′N</field><field name = 'longitude'> 16°24′O</field></record>
<record model = 'res.partner' id = "itk_initial_data_import.gemeinde10907"><field name = 'street'>Bachgasse 2</field><field name = 'website'>www.kemeten.at</field><field name = 'austria_wiki_url'>https://austria-forum.org/af/AustriaWiki/Kemeten</field><field name = 'latitude'>47°15′N</field><field name = 'longitude'> 16°9′O</field></record>
<record model = 'res.partner' id = "itk_initial_data_import.gemeinde10711"><field name = 'street'>Hauptplatz 11</field><field name = 'website'>www.kittsee.at</field><field name = 'austria_wiki_url'>https://austria-forum.org/af/AustriaWiki/Kittsee</field><field name = 'latitude'>48°5′N</field><field name = 'longitude'> 17°4′O</field></record>
<record model = 'res.partner' id = "itk_initial_data_import.gemeinde10305"><field name = 'street'>Grünberggasse 1</field><field name = 'website'>www.klingenbach.info</field><field name = 'austria_wiki_url'>https://austria-forum.org/af/AustriaWiki/Klingenbach</field><field name = 'latitude'>47°45′N</field><field name = 'longitude'> 16°32′O</field></record>
<record model = 'res.partner' id = "itk_initial_data_import.gemeinde10422"><field name = 'street'>Kleinmürbisch 1</field><field name = 'website'>www.kleinmuerbisch.at</field><field name = 'austria_wiki_url'>https://austria-forum.org/af/AustriaWiki/Kleinm%C3%BCrbisch</field><field name = 'latitude'>47°2′N</field><field name = 'longitude'> 16°19′O</field></record>
<record model = 'res.partner' id = "itk_initial_data_import.gemeinde10807"><field name = 'street'>Hauptstraße 38</field><field name = 'website'>www.kobersdorf.at</field><field name = 'austria_wiki_url'>https://austria-forum.org/af/AustriaWiki/Kobersdorf</field><field name = 'latitude'>47°36′N</field><field name = 'longitude'> 16°24′O</field></record>
<record model = 'res.partner' id = "itk_initial_data_import.gemeinde10619"><field name = 'street'> </field><field name = 'website'>www.krensdorf.at</field><field name = 'austria_wiki_url'>https://austria-forum.org/af/AustriaWiki/Krensdorf</field><field name = 'latitude'>47°47′N</field><field name = 'longitude'> 16°25′O</field></record>
<record model = 'res.partner' id = "itk_initial_data_import.gemeinde10908"><field name = 'street'>Marktgemeinde KohfidischObere Hauptstraße 4</field><field name = 'website'>www.kohfidisch.at</field><field name = 'austria_wiki_url'>https://austria-forum.org/af/AustriaWiki/Kohfidisch</field><field name = 'latitude'>47°10′N</field><field name = 'longitude'> 16°21′O</field></record>
<record model = 'res.partner' id = "itk_initial_data_import.gemeinde10511"><field name = 'street'>Dorfstraße 19</field><field name = 'website'>www.koenigsdorf.at</field><field name = 'austria_wiki_url'>https://austria-forum.org/af/AustriaWiki/K%C3%B6nigsdorf_%28Burgenland%29</field><field name = 'latitude'>47°0′N</field><field name = 'longitude'> 16°10′O</field></record>
<record model = 'res.partner' id = "itk_initial_data_import.gemeinde10408"><field name = 'street'>Dorfplatz 2</field><field name = 'website'>www.kukmirn.at</field><field name = 'austria_wiki_url'>https://austria-forum.org/af/AustriaWiki/Kukmirn</field><field name = 'latitude'>47°4′N</field><field name = 'longitude'> 16°12′O</field></record>
<record model = 'res.partner' id = "itk_initial_data_import.gemeinde10808"><field name = 'street'>Postgasse 6</field><field name = 'website'>www.gemeinde-lackenbach.at</field><field name = 'austria_wiki_url'>https://austria-forum.org/af/AustriaWiki/Lackenbach</field><field name = 'latitude'>47°35′N</field><field name = 'longitude'> 16°28′O</field></record>
<record model = 'res.partner' id = "itk_initial_data_import.gemeinde10824"><field name = 'street'>Hauptstrasse 27</field><field name = 'website'>www.lackendorf.at</field><field name = 'austria_wiki_url'>https://austria-forum.org/af/AustriaWiki/Lackendorf</field><field name = 'latitude'>47°35′N</field><field name = 'longitude'> 16°30′O</field></record>
<record model = 'res.partner' id = "itk_initial_data_import.gemeinde10306"><field name = 'street'>Schulgasse 1</field><field name = 'website'>www.leithaprodersdorf.gv.at</field><field name = 'austria_wiki_url'>https://austria-forum.org/af/AustriaWiki/Leithaprodersdorf</field><field name = 'latitude'>47°56′N</field><field name = 'longitude'> 16°29′O</field></record>
<record model = 'res.partner' id = "itk_initial_data_import.gemeinde10810"><field name = 'street'>Neustiftplatz 1</field><field name = 'website'>www.lutzmannsburg.info</field><field name = 'austria_wiki_url'>https://austria-forum.org/af/AustriaWiki/Lutzmannsburg</field><field name = 'latitude'>47°28′N</field><field name = 'longitude'> 16°38′O</field></record>
<record model = 'res.partner' id = "itk_initial_data_import.gemeinde10809"><field name = 'street'>Hauptplatz 10</field><field name = 'website'>www.lockenhaus.at</field><field name = 'austria_wiki_url'>https://austria-forum.org/af/AustriaWiki/Lockenhaus</field><field name = 'latitude'>47°24′N</field><field name = 'longitude'> 16°25′O</field></record>
<record model = 'res.partner' id = "itk_initial_data_import.gemeinde10604"><field name = 'street'>Badstraße 1</field><field name = 'website'>www.loipersbach.info</field><field name = 'austria_wiki_url'>https://austria-forum.org/af/AustriaWiki/Loipersbach_im_Burgenland</field><field name = 'latitude'>47°42′N</field><field name = 'longitude'> 16°28′O</field></record>
<record model = 'res.partner' id = "itk_initial_data_import.gemeinde10320"><field name = 'street'>Hauptplatz 9</field><field name = 'website'>www.gemeinde-loretto.at</field><field name = 'austria_wiki_url'>https://austria-forum.org/af/AustriaWiki/Loretto_%28Burgenland%29</field><field name = 'latitude'>47°55′N</field><field name = 'longitude'> 16°31′O</field></record>
<record model = 'res.partner' id = "itk_initial_data_import.gemeinde10811"><field name = 'street'>Hauptstraße 68</field><field name = 'website'>https://mannersdorfrabnitz.riskommunal.net</field><field name = 'austria_wiki_url'>https://austria-forum.org/af/AustriaWiki/Mannersdorf_an_der_Rabnitz</field><field name = 'latitude'>47°26′N</field><field name = 'longitude'> 16°32′O</field></record>
<record model = 'res.partner' id = "itk_initial_data_import.gemeinde10911"><field name = 'street'>Mariasdorf </field><field name = 'website'>www.mariasdorf.at</field><field name = 'austria_wiki_url'>https://austria-forum.org/af/AustriaWiki/Mariasdorf</field><field name = 'latitude'>47°22′N</field><field name = 'longitude'> 16°14′O</field></record>
<record model = 'res.partner' id = "itk_initial_data_import.gemeinde10912"><field name = 'street'>Gemeindestraße 29</field><field name = 'website'>www.marktallhau.at</field><field name = 'austria_wiki_url'>https://austria-forum.org/af/AustriaWiki/Markt_Allhau</field><field name = 'latitude'>47°17′N</field><field name = 'longitude'> 16°5′O</field></record>
<record model = 'res.partner' id = "itk_initial_data_import.gemeinde10812"><field name = 'street'>Kirchenplatz 17</field><field name = 'website'>www.marktstmartin.at</field><field name = 'austria_wiki_url'>https://austria-forum.org/af/AustriaWiki/Markt_Sankt_Martin</field><field name = 'latitude'>47°34′N</field><field name = 'longitude'> 16°26′O</field></record>
<record model = 'res.partner' id = "itk_initial_data_import.gemeinde10606"><field name = 'street'>Stadtgemeinde MattersburgBrunnenplatz 4</field><field name = 'website'>www.mattersburg.gv.at</field><field name = 'austria_wiki_url'>https://austria-forum.org/af/AustriaWiki/Mattersburg</field><field name = 'latitude'>47°44′N</field><field name = 'longitude'> 16°24′O</field></record>
<record model = 'res.partner' id = "itk_initial_data_import.gemeinde10914"><field name = 'street'> </field><field name = 'website'>www.mischendorf.at</field><field name = 'austria_wiki_url'>https://austria-forum.org/af/AustriaWiki/Mischendorf</field><field name = 'latitude'>47°12′N</field><field name = 'longitude'> 16°19′O</field></record>
<record model = 'res.partner' id = "itk_initial_data_import.gemeinde10505"><field name = 'street'>Minihof-Liebau 25</field><field name = 'website'>www.minihof-liebau.at</field><field name = 'austria_wiki_url'>https://austria-forum.org/af/AustriaWiki/Minihof-Liebau</field><field name = 'latitude'>46°53′N</field><field name = 'longitude'> 16°4′O</field></record>
<record model = 'res.partner' id = "itk_initial_data_import.gemeinde10506"><field name = 'street'>Mogersdorf 2</field><field name = 'website'>www.mogersdorf.at</field><field name = 'austria_wiki_url'>https://austria-forum.org/af/AustriaWiki/Mogersdorf</field><field name = 'latitude'>46°57′N</field><field name = 'longitude'> 16°14′O</field></record>
<record model = 'res.partner' id = "itk_initial_data_import.gemeinde10307"><field name = 'street'>Hauptstraße 22</field><field name = 'website'>www.moerbisch.com</field><field name = 'austria_wiki_url'>https://austria-forum.org/af/AustriaWiki/M%C3%B6rbisch_am_See</field><field name = 'latitude'>47°45′N</field><field name = 'longitude'> 16°40′O</field></record>
<record model = 'res.partner' id = "itk_initial_data_import.gemeinde10428"><field name = 'street'>Moschendorf 95</field><field name = 'website'>www.moschendorf.at/</field><field name = 'austria_wiki_url'>https://austria-forum.org/af/AustriaWiki/Moschendorf_%28Burgenland%29</field><field name = 'latitude'>47°3′N</field><field name = 'longitude'> 16°29′O</field></record>
<record model = 'res.partner' id = "itk_initial_data_import.gemeinde10512"><field name = 'street'>Feldanergraben </field><field name = 'website'>www.muehlgraben.at</field><field name = 'austria_wiki_url'>https://austria-forum.org/af/AustriaWiki/M%C3%BChlgraben_%28Burgenland%29</field><field name = 'latitude'>46°53′N</field><field name = 'longitude'> 16°3′O</field></record>
<record model = 'res.partner' id = "itk_initial_data_import.gemeinde10308"><field name = 'street'>Kapellenplatz 1</field><field name = 'website'>www.muellendorf.at</field><field name = 'austria_wiki_url'>https://austria-forum.org/af/AustriaWiki/M%C3%BCllendorf</field><field name = 'latitude'>47°50′N</field><field name = 'longitude'> 16°27′O</field></record>
<record model = 'res.partner' id = "itk_initial_data_import.gemeinde10813"><field name = 'street'>Rathausgasse 1</field><field name = 'website'>www.neckenmarkt.eu</field><field name = 'austria_wiki_url'>https://austria-forum.org/af/AustriaWiki/Neckenmarkt</field><field name = 'latitude'>47°36′N</field><field name = 'longitude'> 16°33′O</field></record>
<record model = 'res.partner' id = "itk_initial_data_import.gemeinde10409"><field name = 'street'>Hauptplatz 1</field><field name = 'website'>www.neuberg-bgld.at</field><field name = 'austria_wiki_url'>https://austria-forum.org/af/AustriaWiki/Neuberg_im_Burgenland</field><field name = 'latitude'>47°10′N</field><field name = 'longitude'> 16°16′O</field></record>
<record model = 'res.partner' id = "itk_initial_data_import.gemeinde10725"><field name = 'street'>Untere Hauptstraße 2</field><field name = 'website'>www.neudorfbeiparndorf.at</field><field name = 'austria_wiki_url'>https://austria-forum.org/af/AustriaWiki/Neudorf_bei_Parndorf</field><field name = 'latitude'>48°1′N</field><field name = 'longitude'> 16°56′O</field></record>
<record model = 'res.partner' id = "itk_initial_data_import.gemeinde10309"><field name = 'street'>Hauptstraße 55</field><field name = 'website'>www.neufeld-leitha.at</field><field name = 'austria_wiki_url'>https://austria-forum.org/af/AustriaWiki/Neufeld_an_der_Leitha</field><field name = 'latitude'>47°52′N</field><field name = 'longitude'> 16°23′O</field></record>
<record model = 'res.partner' id = "itk_initial_data_import.gemeinde10607"><field name = 'street'>Rathausplatz</field><field name = 'website'>www.neudoerfl.gv.at</field><field name = 'austria_wiki_url'>https://austria-forum.org/af/AustriaWiki/Neud%C3%B6rfl</field><field name = 'latitude'>47°48′N</field><field name = 'longitude'> 16°18′O</field></record>
<record model = 'res.partner' id = "itk_initial_data_import.gemeinde10507"><field name = 'street'>Hauptstraße 25</field><field name = 'website'>www.neuhaus-klausenbach.at</field><field name = 'austria_wiki_url'>https://austria-forum.org/af/AustriaWiki/Neuhaus_am_Klausenbach</field><field name = 'latitude'>46°52′N</field><field name = 'longitude'> 16°2′O</field></record>
<record model = 'res.partner' id = "itk_initial_data_import.gemeinde10814"><field name = 'street'>Hauptstraße 47</field><field name = 'website'>www.neutal.at/gemeinde</field><field name = 'austria_wiki_url'>https://austria-forum.org/af/AustriaWiki/Neutal</field><field name = 'latitude'>47°33′N</field><field name = 'longitude'> 16°27′O</field></record>
<record model = 'res.partner' id = "itk_initial_data_import.gemeinde10713"><field name = 'street'>Hauptplatz 1</field><field name = 'website'>www.neusiedlamsee.at</field><field name = 'austria_wiki_url'>https://austria-forum.org/af/AustriaWiki/Neusiedl_am_See</field><field name = 'latitude'>47°57′N</field><field name = 'longitude'> 16°51′O</field></record>
<record model = 'res.partner' id = "itk_initial_data_import.gemeinde10929"><field name = 'street'>Neustift an der Lafnitz 3</field><field name = 'website'>www.neustift-lafnitz.at</field><field name = 'austria_wiki_url'>https://austria-forum.org/af/AustriaWiki/Neustift_an_der_Lafnitz</field><field name = 'latitude'>47°22′N</field><field name = 'longitude'> 16°2′O</field></record>
<record model = 'res.partner' id = "itk_initial_data_import.gemeinde10410"><field name = 'street'>Neustift bei Güssing 1</field><field name = 'website'>www.neustift-bei-güssing.at</field><field name = 'austria_wiki_url'>https://austria-forum.org/af/AustriaWiki/Neustift_bei_G%C3%BCssing</field><field name = 'latitude'>47°1′N</field><field name = 'longitude'> 16°15′O</field></record>
<record model = 'res.partner' id = "itk_initial_data_import.gemeinde10714"><field name = 'street'>Obere Hauptstraße 3</field><field name = 'website'>www.nickelsdorf.at</field><field name = 'austria_wiki_url'>https://austria-forum.org/af/AustriaWiki/Nickelsdorf</field><field name = 'latitude'>47°56′N</field><field name = 'longitude'> 17°4′O</field></record>
<record model = 'res.partner' id = "itk_initial_data_import.gemeinde10815"><field name = 'street'>Hauptstraße 87</field><field name = 'website'>www.gemeinde-nikitsch.at</field><field name = 'austria_wiki_url'>https://austria-forum.org/af/AustriaWiki/Nikitsch</field><field name = 'latitude'>47°32′N</field><field name = 'longitude'> 16°40′O</field></record>
<record model = 'res.partner' id = "itk_initial_data_import.gemeinde10915"><field name = 'street'>Untere Hauptstraße 9</field><field name = 'website'>nicht bekannt</field><field name = 'austria_wiki_url'>https://austria-forum.org/af/AustriaWiki/Oberdorf_im_Burgenland</field><field name = 'latitude'>47°13′N</field><field name = 'longitude'> 16°13′O</field></record>
<record model = 'res.partner' id = "itk_initial_data_import.gemeinde10828"><field name = 'street'>Hauptstraße 63</field><field name = 'website'>http://www.oberloisdorf.at/</field><field name = 'austria_wiki_url'>https://austria-forum.org/af/AustriaWiki/Oberloisdorf</field><field name = 'latitude'>47°27′N</field><field name = 'longitude'> 16°30′O</field></record>
<record model = 'res.partner' id = "itk_initial_data_import.gemeinde10816"><field name = 'street'>Hauptstraße 9</field><field name = 'website'>www.oberpullendorf.at</field><field name = 'austria_wiki_url'>https://austria-forum.org/af/AustriaWiki/Oberpullendorf</field><field name = 'latitude'>47°30′N</field><field name = 'longitude'> 16°31′O</field></record>
<record model = 'res.partner' id = "itk_initial_data_import.gemeinde10916"><field name = 'street'>Hauptplatz 1</field><field name = 'website'>www.oberschuetzen.at</field><field name = 'austria_wiki_url'>https://austria-forum.org/af/AustriaWiki/Obersch%C3%BCtzen</field><field name = 'latitude'>47°21′N</field><field name = 'longitude'> 16°12′O</field></record>
<record model = 'res.partner' id = "itk_initial_data_import.gemeinde10310"><field name = 'street'>Hauptstraße 52</field><field name = 'website'>www.oggau.at</field><field name = 'austria_wiki_url'>https://austria-forum.org/af/AustriaWiki/Oggau_am_Neusiedler_See</field><field name = 'latitude'>47°50′N</field><field name = 'longitude'> 16°40′O</field></record>
<record model = 'res.partner' id = "itk_initial_data_import.gemeinde10917"><field name = 'street'>Hauptplatz 9</field><field name = 'website'>www.oberwart.at</field><field name = 'austria_wiki_url'>https://austria-forum.org/af/AustriaWiki/Oberwart</field><field name = 'latitude'>47°17′N</field><field name = 'longitude'> 16°12′O</field></record>
<record model = 'res.partner' id = "itk_initial_data_import.gemeinde10412"><field name = 'street'>Gemeindeplatz 1</field><field name = 'website'>www.ollersdorf-burgenland.at</field><field name = 'austria_wiki_url'>https://austria-forum.org/af/AustriaWiki/Ollersdorf_im_Burgenland</field><field name = 'latitude'>47°10′N</field><field name = 'longitude'> 16°10′O</field></record>
<record model = 'res.partner' id = "itk_initial_data_import.gemeinde10411"><field name = 'street'>Dorf 1</field><field name = 'website'>www.olbendorf.at</field><field name = 'austria_wiki_url'>https://austria-forum.org/af/AustriaWiki/Olbendorf</field><field name = 'latitude'>47°11′N</field><field name = 'longitude'> 16°12′O</field></record>
<record model = 'res.partner' id = "itk_initial_data_import.gemeinde10311"><field name = 'street'>Hauptstraße 7</field><field name = 'website'>www.oslip.at</field><field name = 'austria_wiki_url'>https://austria-forum.org/af/AustriaWiki/Oslip</field><field name = 'latitude'>47°50′N</field><field name = 'longitude'> 16°37′O</field></record>
<record model = 'res.partner' id = "itk_initial_data_import.gemeinde10715"><field name = 'street'>Hauptplatz 1</field><field name = 'website'>www.gemeinde-pama.at</field><field name = 'austria_wiki_url'>https://austria-forum.org/af/AustriaWiki/Pama</field><field name = 'latitude'>48°3′N</field><field name = 'longitude'> 17°2′O</field></record>
<record model = 'res.partner' id = "itk_initial_data_import.gemeinde10716"><field name = 'street'>Hauptstraße 7</field><field name = 'website'>www.gemeinde-pamhagen.at</field><field name = 'austria_wiki_url'>https://austria-forum.org/af/AustriaWiki/Pamhagen</field><field name = 'latitude'>47°42′N</field><field name = 'longitude'> 16°54′O</field></record>
<record model = 'res.partner' id = "itk_initial_data_import.gemeinde10817"><field name = 'street'>Kirchschlager Str. 2</field><field name = 'website'>www.pilgersdorf.at</field><field name = 'austria_wiki_url'>https://austria-forum.org/af/AustriaWiki/Pilgersdorf</field><field name = 'latitude'>47°26′N</field><field name = 'longitude'> 16°21′O</field></record>
<record model = 'res.partner' id = "itk_initial_data_import.gemeinde10818"><field name = 'street'>Bundesstraße 14</field><field name = 'website'>www.piringsdorf.at</field><field name = 'austria_wiki_url'>https://austria-forum.org/af/AustriaWiki/Piringsdorf</field><field name = 'latitude'>47°27′N</field><field name = 'longitude'> 16°25′O</field></record>
<record model = 'res.partner' id = "itk_initial_data_import.gemeinde10718"><field name = 'street'>Hauptstraße 2</field><field name = 'website'>Podersdorf am See</field><field name = 'austria_wiki_url'>https://austria-forum.org/af/AustriaWiki/Podersdorf_am_See</field><field name = 'latitude'>47°51′N</field><field name = 'longitude'> 16°50′O</field></record>
<record model = 'res.partner' id = "itk_initial_data_import.gemeinde10918"><field name = 'street'>Hauptplatz 1</field><field name = 'website'>www.pinkafeld-online.at</field><field name = 'austria_wiki_url'>https://austria-forum.org/af/AustriaWiki/Pinkafeld</field><field name = 'latitude'>47°22′N</field><field name = 'longitude'> 16°7′O</field></record>
<record model = 'res.partner' id = "itk_initial_data_import.gemeinde10427"><field name = 'street'>Hauptplatz 8</field><field name = 'website'>www.rauchwart.at</field><field name = 'austria_wiki_url'>https://austria-forum.org/af/AustriaWiki/Rauchwart</field><field name = 'latitude'>47°8′N</field><field name = 'longitude'> 16°14′O</field></record>
<record model = 'res.partner' id = "itk_initial_data_import.gemeinde10726"><field name = 'street'>Untere Hauptstraße 26</field><field name = 'website'>www.potzneusiedl.at</field><field name = 'austria_wiki_url'>https://austria-forum.org/af/AustriaWiki/Potzneusiedl</field><field name = 'latitude'>48°3′N</field><field name = 'longitude'> 16°57′O</field></record>
<record model = 'res.partner' id = "itk_initial_data_import.gemeinde10312"><field name = 'street'>Hauptgasse 38</field><field name = 'website'>www.purbach.at</field><field name = 'austria_wiki_url'>https://austria-forum.org/af/AustriaWiki/Purbach_am_Neusiedler_See</field><field name = 'latitude'>47°55′N</field><field name = 'longitude'> 16°42′O</field></record>
<record model = 'res.partner' id = "itk_initial_data_import.gemeinde10819"><field name = 'street'>Franz Liszt-Platz 1</field><field name = 'website'>www.raiding-online.at</field><field name = 'austria_wiki_url'>https://austria-forum.org/af/AustriaWiki/Raiding</field><field name = 'latitude'>47°34′N</field><field name = 'longitude'> 16°32′O</field></record>
<record model = 'res.partner' id = "itk_initial_data_import.gemeinde10820"><field name = 'street'>Lange Zeile 21</field><field name = 'website'>www.ritzing.at</field><field name = 'austria_wiki_url'>https://austria-forum.org/af/AustriaWiki/Ritzing_%28Burgenland%29</field><field name = 'latitude'>47°37′N</field><field name = 'longitude'> 16°30′O</field></record>
<record model = 'res.partner' id = "itk_initial_data_import.gemeinde10920"><field name = 'street'>Obere Hauptstraße 1</field><field name = 'website'>www.riedlingsdorf.at</field><field name = 'austria_wiki_url'>https://austria-forum.org/af/AustriaWiki/Riedlingsdorf</field><field name = 'latitude'>47°21′N</field><field name = 'longitude'> 16°8′O</field></record>
<record model = 'res.partner' id = "itk_initial_data_import.gemeinde10425"><field name = 'street'>Rohr im Burgenland 150</field><field name = 'website'>nicht bekannt</field><field name = 'austria_wiki_url'>https://austria-forum.org/af/AustriaWiki/Rohr_im_Burgenland</field><field name = 'latitude'>47°7′N</field><field name = 'longitude'> 16°10′O</field></record>
<record model = 'res.partner' id = "itk_initial_data_import.gemeinde10719"><field name = 'street'>Hauptstraße 59</field><field name = 'website'>www.standraezicksee.at</field><field name = 'austria_wiki_url'>https://austria-forum.org/af/AustriaWiki/Sankt_Andr%C3%A4_am_Zicksee</field><field name = 'latitude'>47°47′N</field><field name = 'longitude'> 16°56′O</field></record>
<record model = 'res.partner' id = "itk_initial_data_import.gemeinde10508"><field name = 'street'>Kirchenplatz 1</field><field name = 'website'>www.rudersdorf.at</field><field name = 'austria_wiki_url'>https://austria-forum.org/af/AustriaWiki/Rudersdorf_%28Burgenland%29</field><field name = 'latitude'>47°3′N</field><field name = 'longitude'> 16°7′O</field></record>
<record model = 'res.partner' id = "itk_initial_data_import.gemeinde10921"><field name = 'street'> </field><field name = 'website'>nicht bekannt</field><field name = 'austria_wiki_url'>https://austria-forum.org/af/AustriaWiki/Rotenturm_an_der_Pinka</field><field name = 'latitude'>47°15′N</field><field name = 'longitude'> 16°15′O</field></record>
<record model = 'res.partner' id = "itk_initial_data_import.gemeinde10201"><field name = 'street'>Conradplatz 1</field><field name = 'website'>www.rust.at</field><field name = 'austria_wiki_url'>https://austria-forum.org/af/AustriaWiki/Rust_%28Burgenland%29</field><field name = 'latitude'>47°48′N</field><field name = 'longitude'> 16°41′O</field></record>
<record model = 'res.partner' id = "itk_initial_data_import.gemeinde10509"><field name = 'street'>Hauptplatz 7</field><field name = 'website'>www.sankt-martin-raab.at</field><field name = 'austria_wiki_url'>https://austria-forum.org/af/AustriaWiki/Sankt_Martin_an_der_Raab</field><field name = 'latitude'>46°55′N</field><field name = 'longitude'> 16°8′O</field></record>
<record model = 'res.partner' id = "itk_initial_data_import.gemeinde10313"><field name = 'street'>Hauptplatz 1</field><field name = 'website'>www.st-margarethen.at</field><field name = 'austria_wiki_url'>https://austria-forum.org/af/AustriaWiki/Sankt_Margarethen_im_Burgenland</field><field name = 'latitude'>47°48′N</field><field name = 'longitude'> 16°36′O</field></record>
<record model = 'res.partner' id = "itk_initial_data_import.gemeinde10413"><field name = 'street'>Hauptplatz 8</field><field name = 'website'>www.st.michael-bgld.at</field><field name = 'austria_wiki_url'>https://austria-forum.org/af/AustriaWiki/Sankt_Michael_im_Burgenland</field><field name = 'latitude'>47°8′N</field><field name = 'longitude'> 16°16′O</field></record>
<record model = 'res.partner' id = "itk_initial_data_import.gemeinde10932"><field name = 'street'>Schandorf 150</field><field name = 'website'>www.schandorf.at</field><field name = 'austria_wiki_url'>https://austria-forum.org/af/AustriaWiki/Schandorf</field><field name = 'latitude'>47°15′N</field><field name = 'longitude'> 16°25′O</field></record>
<record model = 'res.partner' id = "itk_initial_data_import.gemeinde10612"><field name = 'street'> </field><field name = 'website'>www.schattendorf.at</field><field name = 'austria_wiki_url'>https://austria-forum.org/af/AustriaWiki/Schattendorf</field><field name = 'latitude'>47°43′N</field><field name = 'longitude'> 16°31′O</field></record>
<record model = 'res.partner' id = "itk_initial_data_import.gemeinde10314"><field name = 'street'>Dorfplatz 1</field><field name = 'website'>www.schuetzen-am-gebirge.at</field><field name = 'austria_wiki_url'>https://austria-forum.org/af/AustriaWiki/Sch%C3%BCtzen_am_Gebirge</field><field name = 'latitude'>47°51′N</field><field name = 'longitude'> 16°37′O</field></record>
<record model = 'res.partner' id = "itk_initial_data_import.gemeinde10315"><field name = 'street'>Rathausplatz 1</field><field name = 'website'>www.siegendorf.at</field><field name = 'austria_wiki_url'>https://austria-forum.org/af/AustriaWiki/Siegendorf</field><field name = 'latitude'>47°47′N</field><field name = 'longitude'> 16°32′O</field></record>
<record model = 'res.partner' id = "itk_initial_data_import.gemeinde10414"><field name = 'street'>Hauptplatz 7</field><field name = 'website'>gemeinde.stegersbach.at</field><field name = 'austria_wiki_url'>https://austria-forum.org/af/AustriaWiki/Stegersbach</field><field name = 'latitude'>47°10′N</field><field name = 'longitude'> 16°10′O</field></record>
<record model = 'res.partner' id = "itk_initial_data_import.gemeinde10316"><field name = 'street'>Obere Hauptstraße 1</field><field name = 'website'>www.steinbrunn.at</field><field name = 'austria_wiki_url'>https://austria-forum.org/af/AustriaWiki/Steinbrunn</field><field name = 'latitude'>47°50′N</field><field name = 'longitude'> 16°25′O</field></record>
<record model = 'res.partner' id = "itk_initial_data_import.gemeinde10415"><field name = 'street'>Hauptplatz 1</field><field name = 'website'>stinatz.gv.at</field><field name = 'austria_wiki_url'>https://austria-forum.org/af/AustriaWiki/Stinatz</field><field name = 'latitude'>47°12′N</field><field name = 'longitude'> 16°8′O</field></record>
<record model = 'res.partner' id = "itk_initial_data_import.gemeinde10822"><field name = 'street'>Hauptstraße 72</field><field name = 'website'>www.stoob.at</field><field name = 'austria_wiki_url'>https://austria-forum.org/af/AustriaWiki/Stoob</field><field name = 'latitude'>47°32′N</field><field name = 'longitude'> 16°29′O</field></record>
<record model = 'res.partner' id = "itk_initial_data_import.gemeinde10321"><field name = 'street'>Feldgasse 2</field><field name = 'website'>www.stotzing.at</field><field name = 'austria_wiki_url'>https://austria-forum.org/af/AustriaWiki/Stotzing</field><field name = 'latitude'>47°54′N</field><field name = 'longitude'> 16°33′O</field></record>
<record model = 'res.partner' id = "itk_initial_data_import.gemeinde10416"><field name = 'street'>Lindenstraße 1</field><field name = 'website'>www.strem.co.at</field><field name = 'austria_wiki_url'>https://austria-forum.org/af/AustriaWiki/Strem</field><field name = 'latitude'>47°3′N</field><field name = 'longitude'> 16°25′O</field></record>
<record model = 'res.partner' id = "itk_initial_data_import.gemeinde10825"><field name = 'street'>Hauptstraße 28</field><field name = 'website'>www.unterfrauenhaid.at</field><field name = 'austria_wiki_url'>https://austria-forum.org/af/AustriaWiki/Unterfrauenhaid</field><field name = 'latitude'>47°34′N</field><field name = 'longitude'> 16°30′O</field></record>
<record model = 'res.partner' id = "itk_initial_data_import.gemeinde10417"><field name = 'street'>Tobaj 107</field><field name = 'website'>www.tobaj.gv.at</field><field name = 'austria_wiki_url'>https://austria-forum.org/af/AustriaWiki/Tobaj</field><field name = 'latitude'>47°5′N</field><field name = 'longitude'> 16°18′O</field></record>
<record model = 'res.partner' id = "itk_initial_data_import.gemeinde10720"><field name = 'street'>Obere Hauptstraße 1</field><field name = 'website'>http://www.tadten.eu</field><field name = 'austria_wiki_url'>https://austria-forum.org/af/AustriaWiki/Tadten</field><field name = 'latitude'>47°46′N</field><field name = 'longitude'> 16°59′O</field></record>
<record model = 'res.partner' id = "itk_initial_data_import.gemeinde10317"><field name = 'street'>DDr. Stefan Laszlo Platz 3</field><field name = 'website'>www.trausdorf-wulka.gv.at</field><field name = 'austria_wiki_url'>https://austria-forum.org/af/AustriaWiki/Trausdorf_an_der_Wulka</field><field name = 'latitude'>47°49′N</field><field name = 'longitude'> 16°33′O</field></record>
<record model = 'res.partner' id = "itk_initial_data_import.gemeinde10423"><field name = 'street'>Tschanigraben 1</field><field name = 'website'>http://www.tschanigraben.at</field><field name = 'austria_wiki_url'>https://austria-forum.org/af/AustriaWiki/Tschanigraben</field><field name = 'latitude'>47°0′N</field><field name = 'longitude'> 16°18′O</field></record>
<record model = 'res.partner' id = "itk_initial_data_import.gemeinde10721"><field name = 'street'>Hauptstraße 4</field><field name = 'website'>www.marktgemeinde-wallern-im-burgenland.at</field><field name = 'austria_wiki_url'>https://austria-forum.org/af/AustriaWiki/Wallern_im_Burgenland</field><field name = 'latitude'>47°44′N</field><field name = 'longitude'> 16°56′O</field></record>
<record model = 'res.partner' id = "itk_initial_data_import.gemeinde10924"><field name = 'street'>Unterkohlstätten 32</field><field name = 'website'>www.unterkohlstaetten.at</field><field name = 'austria_wiki_url'>https://austria-forum.org/af/AustriaWiki/Unterkohlst%C3%A4tten</field><field name = 'latitude'>47°23′N</field><field name = 'longitude'> 16°19′O</field></record>
<record model = 'res.partner' id = "itk_initial_data_import.gemeinde10925"><field name = 'street'>Unterwart 230</field><field name = 'website'>www.unterwart.at</field><field name = 'austria_wiki_url'>https://austria-forum.org/af/AustriaWiki/Unterwart</field><field name = 'latitude'>47°16′N</field><field name = 'longitude'> 16°14′O</field></record>
<record model = 'res.partner' id = "itk_initial_data_import.gemeinde10926"><field name = 'street'>Weiden bei Rechnitz 64</field><field name = 'website'>www.weiden-rechnitz.at</field><field name = 'austria_wiki_url'>https://austria-forum.org/af/AustriaWiki/Weiden_bei_Rechnitz</field><field name = 'latitude'>47°18′N</field><field name = 'longitude'> 16°21′O</field></record>
<record model = 'res.partner' id = "itk_initial_data_import.gemeinde10722"><field name = 'street'>Raiffeisenplatz 5</field><field name = 'website'>www.weiden-see.at</field><field name = 'austria_wiki_url'>https://austria-forum.org/af/AustriaWiki/Weiden_am_See</field><field name = 'latitude'>47°56′N</field><field name = 'longitude'> 16°52′O</field></record>
<record model = 'res.partner' id = "itk_initial_data_import.gemeinde10827"><field name = 'street'>Hauptplatz 5</field><field name = 'website'>nicht bekannt</field><field name = 'austria_wiki_url'>https://austria-forum.org/af/AustriaWiki/Weingraben</field><field name = 'latitude'>47°31′N</field><field name = 'longitude'> 16°22′O</field></record>
<record model = 'res.partner' id = "itk_initial_data_import.gemeinde10823"><field name = 'street'>Hauptstraße 104</field><field name = 'website'>www.weppersdorf.at</field><field name = 'austria_wiki_url'>https://austria-forum.org/af/AustriaWiki/Weppersdorf</field><field name = 'latitude'>47°35′N</field><field name = 'longitude'> 16°26′O</field></record>
<record model = 'res.partner' id = "itk_initial_data_import.gemeinde10927"><field name = 'street'>Wiesfleck 80</field><field name = 'website'>www.wiesfleck.at</field><field name = 'austria_wiki_url'>https://austria-forum.org/af/AustriaWiki/Wiesfleck</field><field name = 'latitude'>47°23′N</field><field name = 'longitude'> 16°9′O</field></record>
<record model = 'res.partner' id = "itk_initial_data_import.gemeinde10723"><field name = 'street'>Hauptstraße 8</field><field name = 'website'>www.winden.at</field><field name = 'austria_wiki_url'>https://austria-forum.org/af/AustriaWiki/Winden_am_See</field><field name = 'latitude'>47°57′N</field><field name = 'longitude'> 16°45′O</field></record>
<record model = 'res.partner' id = "itk_initial_data_import.gemeinde10928"><field name = 'street'>Hauptstraße 43</field><field name = 'website'>www.wolfau.at</field><field name = 'austria_wiki_url'>https://austria-forum.org/af/AustriaWiki/Wolfau</field><field name = 'latitude'>47°15′N</field><field name = 'longitude'> 16°6′O</field></record>
<record model = 'res.partner' id = "itk_initial_data_import.gemeinde10318"><field name = 'street'>Kirchengasse 12</field><field name = 'website'>www.wimpassing-leitha.at</field><field name = 'austria_wiki_url'>https://austria-forum.org/af/AustriaWiki/Wimpassing_an_der_Leitha</field><field name = 'latitude'>47°55′N</field><field name = 'longitude'> 16°26′O</field></record>
<record model = 'res.partner' id = "itk_initial_data_import.gemeinde10419"><field name = 'street'>Wörterberg 49</field><field name = 'website'>www.woerterberg.at</field><field name = 'austria_wiki_url'>https://austria-forum.org/af/AustriaWiki/W%C3%B6rterberg</field><field name = 'latitude'>47°14′N</field><field name = 'longitude'> 16°6′O</field></record>
<record model = 'res.partner' id = "itk_initial_data_import.gemeinde10319"><field name = 'street'>Obere Hauptstraße 1</field><field name = 'website'>www.wulkaprodersdorf.at</field><field name = 'austria_wiki_url'>https://austria-forum.org/af/AustriaWiki/Wulkaprodersdorf</field><field name = 'latitude'>47°48′N</field><field name = 'longitude'> 16°30′O</field></record>
<record model = 'res.partner' id = "itk_initial_data_import.gemeinde10323"><field name = 'street'>Hauptstraße 15</field><field name = 'website'>www.zagersdorf.at</field><field name = 'austria_wiki_url'>https://austria-forum.org/af/AustriaWiki/Zagersdorf</field><field name = 'latitude'>47°46′N</field><field name = 'longitude'> 16°31′O</field></record>
<record model = 'res.partner' id = "itk_initial_data_import.gemeinde10322"><field name = 'street'>Landstraße 3</field><field name = 'website'>www.zillingtal.eu</field><field name = 'austria_wiki_url'>https://austria-forum.org/af/AustriaWiki/Zillingtal</field><field name = 'latitude'>47°49′N</field><field name = 'longitude'> 16°25′O</field></record>
<record model = 'res.partner' id = "itk_initial_data_import.gemeinde10724"><field name = 'street'>Untere Hauptstraße 4</field><field name = 'website'>www.zurndorf.at</field><field name = 'austria_wiki_url'>https://austria-forum.org/af/AustriaWiki/Zurndorf</field><field name = 'latitude'>47°59′N</field><field name = 'longitude'> 17°0′O</field></record>
</data>
</odoo>
